{
  "titulo": "Cazadores en tierra inhóspita",
  "original": "황야",
  "sinopsis": "Después de un terremoto que convierte Seúl en una tierra inhóspita y sin ley, un cazador entra en acción para rescatar a una chica en manos de un médico trastornado.",
  "estreno": "2024-01-26",
  "puntuacion": 6.7,
  "poster": "/jPGbcbMlzGUECukPhkEMVt1Kvs5.jpg",
  "backdrop": "/xk8CF3DAmiqLFI2YZAmxEJFqI1q.jpg",
  "video_url": "https://grrfff66me7t.objectstorage.sa-saopaulo-1.oci.customer-oci.com/n/grrfff66me7t/b/Cubojoselyn/o/reset%2Fpeliculas%2Fene24%2FVer%20Cazadores%20en%20tierra%20inh%C3%B3spita%20online%20HD%20-%20Cuevana%202.mp4"
}