{
  "titulo": "Luca",
  "original": "Luca",
  "sinopsis": "Ambientada en un precioso pueblo costero de la Riviera italiana, narra la historia sobre el paso a la edad adulta de un chico que vive un verano inolvidable lleno de helados, pasta e infinitos paseos en scooter. Luca comparte estas aventuras con su nuevo mejor amigo, pero toda la diversión se ve amenazada por un secreto muy profundo: él es un monstruo marino de un mundo que yace bajo la superficie del agua.",
  "estreno": "2021-06-17",
  "puntuacion": 7.79,
  "poster": "/pr06RihHOGE3waZQx5fs2WYUdwr.jpg",
  "backdrop": "/620hnMVLu6RSZW6a5rwO8gqpt0t.jpg",
  "video_url": "https://objectstorage.us-phoenix-1.oraclecloud.com/n/axa4wow3dcia/b/bucket-20201001-1658/o/pelis%2Fpelisjun%2Fluca.mp4"
}