{
  "titulo": "El fantástico Halloween de Tibucán",
  "original": "Sharkdog’s Fintastic Halloween",
  "sinopsis": "La pandilla calienta motores para Halloween con la espeluznante leyenda de la niebla aterradora. Tibucán deberá salvar la tradición de truco o trato de un monstruo marino.",
  "estreno": "2021-10-15",
  "puntuacion": 5.5,
  "poster": "/dS2VhPdFOCzqpUT7agGhAJukXso.jpg",
  "backdrop": "/n9ikn33MeCpYyHN7apLj7QgQv0V.jpg",
  "video_url": "https://archive.org/download/01_20211017_202110/01.mp4"
}