{
  "titulo": "Los Juegos del Hambre: Sinsajo - Parte 2",
  "original": "The Hunger Games: Mockingjay - Part 2",
  "sinopsis": "La última entrega de 'Los Juegos del Hambre' nos muestra a una nación en guerra, en la que Katniss se enfrenta con uñas y dientes al presidente Snow. Con la ayuda de algunos amigos, entre ellos Gale, Finnick y Peeta, arriesgará la vida para salir del Distrito 13 y eliminar al presidente Snow.",
  "estreno": "2015-11-18",
  "puntuacion": 6.9,
  "poster": "/3qQPBc7JVGXJGo0Av5jrqndcdTm.jpg",
  "backdrop": "/qVgLMRVNB5bHU0inmRa0ueShacN.jpg",
  "video_url": "http://archive.org/download/ezra_2/subid0_par4_stre4ming_a85/4.mkv"
}