{
  "titulo": "Cementerio viviente",
  "original": "Pet Sematary",
  "sinopsis": "Louis Creed, su esposa y sus dos niños se instalan en una vivienda próxima a una carretera con mucho tráfico. Cerca de la casa hay un sendero que lleva a un cementerio de animales y también a un antiguo cementerio indio; según la leyenda, los que sean enterrados allí volverán a la vida. Cuando uno de los niños muere atropellado por un camión, Louis ldecide enterrarlo en el cementerio indio.",
  "estreno": "1989-04-21",
  "puntuacion": 6.635,
  "poster": "/rjL6WhvdnaEqwMfM3Crscjs0nNP.jpg",
  "backdrop": "/xWq3T9P4NU2pTdZ3hXFygsNnAq4.jpg",
  "video_url": "http://208.88.245.81/nuevo/cementerio.mascotas.elorigen.dual2023.mkv"
}