{
  "titulo": "Los nuevos ricos",
  "original": "The Beverly Hillbillies",
  "tipo": "tv",
  "sinopsis": " Los Clampett son una familia de montañeses que descubren petróleo en sus tierras; se convierten en ricos y se mudan a California. Ahora son los nuevos ricos de Berverly Hills y no se molestarán en esconder sus costumbres. La serie tuvo un enorme éxito en Estados Unidos.",
  "estreno": "1962-09-26",
  "puntuacion": 6.9,
  "poster": "/sEZs4szkwBXIK3DOm37MnQN9fIe.jpg",
  "backdrop": "/nA19z9LnWYebUt3iqoYvkwRKIUI.jpg",
  "video_url": "https://grrfff66me7t.objectstorage.sa-saopaulo-1.oci.customer-oci.com/n/grrfff66me7t/b/Cubojoselyn/o/reset%2Fpeliculas%2Fnoviembre%2FVer%20Nouveaux%20riches%20online%20HD%20-%20Cuevana%202.mp4"
}