{
  "titulo": "Unos suegros de armas tomar",
  "original": "The Out-Laws",
  "sinopsis": "Owen Browning (Adam Devine) es un estirado director de banco que está a punto de casarse con Parker, el amor de su vida. En la semana en la que se va a celebrar su boda, su banco es asaltado por los infames Ghost Bandits, y Owen sospecha que estos viles delincuentes son en realidad sus futuros suegros, que acaban de llegar a la ciudad.",
  "estreno": "2023-07-07",
  "puntuacion": 5.988,
  "poster": "/6SCokFkHM5dTTTfiGXmPWysucMX.jpg",
  "backdrop": "/fjWcAbHRxCSR4kLGvsPEhNjR2ts.jpg",
  "video_url": "https://objectstorage.sa-saopaulo-1.oraclecloud.com/n/grrfff66me7t/b/Cubojoselyn/o/reset%2Fpeliculas%2Fjulio%2FVer%20Unos%20suegros%20de%20armas%20tomar%20online%20HD%20-%20Cuevana%202%20Espa%C3%B1ol.mp4"
}