{
  "titulo": "Oppenheimer",
  "original": "Oppenheimer",
  "tipo": "movie",
  "sinopsis": "Película sobre el físico J. Robert Oppenheimer y su papel como desarrollador de la bomba atómica. Basada en el libro 'American Prometheus: The Triumph and Tragedy of J. Robert Oppenheimer' de Kai Bird y Martin J. Sherwin.",
  "estreno": "2023-07-19",
  "puntuacion": 8.041,
  "poster": "/5t05uhX5ULn8Um2f1ZuznVvIffU.jpg",
  "backdrop": "/ycnO0cjsAROSGJKuMODgRtWsHQw.jpg",
  "video_url": "https://axa4wow3dcia.objectstorage.us-phoenix-1.oci.customer-oci.com/n/axa4wow3dcia/b/bucket-20201001-1658/o/2023pelis%2Fjulio%2FVer%20Oppenheimer%20Online%20Castellano%20Latino%20Subtitulada%20HD%20-%20HDFull.mp4"
}